{
  "/bigmacsmiles": {"Emotes": {"": {"Image": "//c.thumbs.redditmedia.com/Ta6Ub_vPmCf7Pkbh.png", "Size": [100, 100]}}},
  "/bigmouthmac": {"Emotes": {"": {"Image": "//b.thumbs.redditmedia.com/jXsAFBbgLFWSWSYmNe1pEc0d4xoUsnsABSTeeH4teoY.png", "Size": [100, 131]}}},
  "/bouncingmac": {"Emotes": {"": {"Image": "//b.thumbs.redditmedia.com/I1PmJoXy2dNetm4a.png", "Size": [127, 150]}}},
  "/cheer": {"Emotes": {"": {"CSS": {"background-position": "-0px -0px"}, "Type": "Custom"}}},
  "/confusedmac": {"Emotes": {"": {"Image": "//c.thumbs.redditmedia.com/ekCM9faPg70Tc8Jn.png", "Size": [122, 150]}}},
  "/eeyup": {"Emotes": {"": {"CSS": {"background-position": "-0px -0px"}, "Type": "Custom"}}},
  "/farmermac": {"Emotes": {"": {"Image": "//b.thumbs.redditmedia.com/X_yj4OcfrDV2DLCa.png", "Size": [119, 150]}}},
  "/guiltymac": {"Emotes": {"": {"Image": "//b.thumbs.redditmedia.com/r0arCa7GEO58envmDS1o6okyPgIfT1iZ_ZNGNlTrKHU.png", "Size": [150, 186]}}},
  "/lilmac": {"Emotes": {"": {"Image": "//d.thumbs.redditmedia.com/4j9quNfmhFSO3l1Q.png", "Size": [133, 150]}}},
  "/maccheer": {"Emotes": {"": {"Image": "//a.thumbs.redditmedia.com/JVmEfa-FJV8LCzGx.png", "Size": [80, 80]}}},
  "/machappy": {"Emotes": {"": {"Image": "//e.thumbs.redditmedia.com/ibNKjyiFnHSKyS_X.png", "Size": [80, 80]}}},
  "/macismad": {"Emotes": {"": {"Image": "//a.thumbs.redditmedia.com/YNfiKQgjDZc0KdTB.png", "Size": [96, 150]}}},
  "/macntea": {"Emotes": {"": {"Image": "//e.thumbs.redditmedia.com/Hj_9UaQiUIWSxuK4.png", "Size": [120, 150]}}},
  "/macsalute": {"Emotes": {"": {"Image": "//d.thumbs.redditmedia.com/NNuPXb0IjLo_LERo.png", "Size": [200, 106]}}},
  "/nodinmac": {"Emotes": {"": {"Image": "//e.thumbs.redditmedia.com/vIVmtTh_tvzYQoRp.png", "Size": [173, 140]}}},
  "/rcheer": {"Emotes": {"": {"CSS": {"background-position": "-0px -0px"}, "Type": "Custom"}}},
  "/reeyup": {"Emotes": {"": {"CSS": {"background-position": "-0px -0px"}, "Type": "Custom"}}},
  "/rmacntea": {"Emotes": {"": {"CSS": {"background-position": "-0px -0px"}, "Type": "Custom"}}},
  "/rnodinmac": {"Emotes": {"": {"CSS": {"background-position": "-0px -0px"}, "Type": "Custom"}}},
  "/rsadintosh": {"Emotes": {"": {"CSS": {"background-position": "-0px -0px"}, "Type": "Custom"}}},
  "/rsohappy": {"Emotes": {"": {"CSS": {"background-position": "-0px -0px"}, "Type": "Custom"}}},
  "/rswag": {"Emotes": {"": {"CSS": {"background-position": "-0px -0px"}, "Type": "Custom"}}},
  "/rswagintosh": {"Emotes": {"": {"CSS": {"background-position": "-0px -0px"}, "Type": "Custom"}}},
  "/rwutintosh": {"Emotes": {"": {"CSS": {"background-position": "-0px -0px"}, "Type": "Custom"}}},
  "/sadintosh": {"Emotes": {"": {"CSS": {"background-position": "-0px -0px"}, "Type": "Custom"}}},
  "/sohappy": {"Emotes": {"": {"CSS": {"background-position": "-0px -0px"}, "Type": "Custom"}}},
  "/swag": {"Emotes": {"": {"CSS": {"background-position": "-0px -0px"}, "Type": "Custom"}}},
  "/swagintosh": {"Emotes": {"": {"CSS": {"background-position": "-0px -0px"}, "Type": "Custom"}}},
  "/thinkingmac": {"Emotes": {"": {"Image": "//a.thumbs.redditmedia.com/AmKHB3pXrpEJbkOpsC1zH4zAxxH2_Z0-E5F-CHkIDn4.png", "Size": [150, 134]}}},
  "/wutintosh": {"Emotes": {"": {"CSS": {"background-position": "-0px -0px"}, "Type": "Custom"}}}
}