{
  "/abouttoburst": {"Emotes": {"": {"Image": "//b.thumbs.redditmedia.com/zaq8J0atNAFvcoaI9KE_2qIhhrPCMk6Wjt7NqFdWEjg.png", "Offset": [-193, 0], "Size": [200, 181]}}},
  "/abpresenting": {"Emotes": {"": {"Image": "//b.thumbs.redditmedia.com/kf2kLPkoDns8fsQMJK_lwyJ7x1YdccE8qnapjdjx_dA.png", "Offset": [-200, -800], "Size": [200, 190]}}},
  "/acexlefty": {"Emotes": {"": {"Image": "//b.thumbs.redditmedia.com/Enb6P1KwmNZWrR1z-MlIF0yt_FL6Rgz_3iaTbzhmUts.png", "Offset": [-250, -177], "Size": [200, 117]}}},
  "/ajcumshot": {"Emotes": {"": {"Image": "//b.thumbs.redditmedia.com/DsWGGcXEX1Ug2P_GncrEAcvZCt5JykOOGdKkZwW9Tqk.png", "Size": [165, 200]}}},
  "/applesocks": {"Emotes": {"": {"Image": "//b.thumbs.redditmedia.com/TSkLNKAc_OHKjIgFh0vIX89QsvlkmHhBNeYw3Fu1i5o.png", "Offset": [0, -193], "Size": [144, 225]}}},
  "/artimiscock": {"Emotes": {"": {"Image": "//b.thumbs.redditmedia.com/T6ZFnHbsQwhBNyGQUkw2_gzNSvKAI7_ofyoqHwEke2I.png", "Offset": [0, -380], "Size": [250, 148]}}},
  "/asstoass": {"Emotes": {"": {"Image": "//c.thumbs.redditmedia.com/B3C9wC-DnyjmajSJ.png", "Size": [200, 200]}}},
  "/babsbutt": {"Emotes": {"": {"Image": "//b.thumbs.redditmedia.com/kf2kLPkoDns8fsQMJK_lwyJ7x1YdccE8qnapjdjx_dA.png", "Offset": [-345, -434], "Size": [136, 200]}}},
  "/bbinsocks": {"Emotes": {"": {"Image": "//b.thumbs.redditmedia.com/R67XTkTAQExqJDkM.png", "Offset": [-170, -700], "Size": [225, 174]}}},
  "/blueballs": {"Emotes": {"": {"Image": "//b.thumbs.redditmedia.com/zaq8J0atNAFvcoaI9KE_2qIhhrPCMk6Wjt7NqFdWEjg.png", "Offset": [-195, -181], "Size": [199, 250]}}},
  "/bookcatbird": {"Emotes": {"": {"Image": "//b.thumbs.redditmedia.com/DsWGGcXEX1Ug2P_GncrEAcvZCt5JykOOGdKkZwW9Tqk.png", "Offset": [0, -205], "Size": [250, 174]}}},
  "/braebend": {"Emotes": {"": {"Image": "//b.thumbs.redditmedia.com/l1lKBLkm_jPDto3U5Wqv_6QNBPyssrk7uYudHYRZb2g.png", "Offset": [0, -400], "Size": [250, 225]}}},
  "/braeburnrope": {"Emotes": {"": {"Image": "//b.thumbs.redditmedia.com/_sJ6RIQzUs76jyIdOP5QKbrmPZQL5GJ9KMNmVKjm-4c.png", "Offset": [0, -452], "Size": [200, 164]}}},
  "/bringingsexyrap": {"Emotes": {"": {"Image": "//b.thumbs.redditmedia.com/SpfstL_D0xmjEXXMht3KKJXCIxrTXf5vVVtQAG_gJjU.png", "Offset": [-214, -650], "Size": [167, 250]}}},
  "/brushmyass": {"Emotes": {"": {"Image": "//b.thumbs.redditmedia.com/DQyr3kv0V18rANVNJimxQowdxtEjuLuflqEOactFMDo.png", "Offset": [-250, -250], "Size": [250, 250]}}},
  "/burchy": {"Emotes": {"": {"Image": "//b.thumbs.redditmedia.com/2hUZ7DpnWH9RktR_p9-79ZwJkeQCUEGF3O5Uo2XMiCk.png", "Offset": [-250, 0], "Size": [200, 150]}}},
  "/cadancebj": {"Emotes": {"": {"Image": "//a.thumbs.redditmedia.com/if7jlDu9_S2gUGK3nvH0fMOA1WfSOX1FVGosl9MD_78.png", "Offset": [-200, -600], "Size": [200, 200]}}},
  "/cadgym": {"Emotes": {"": {"Image": "//b.thumbs.redditmedia.com/DQyr3kv0V18rANVNJimxQowdxtEjuLuflqEOactFMDo.png", "Offset": [-750, 0], "Size": [250, 250]}}},
  "/celestbj": {"Emotes": {"": {"Image": "//b.thumbs.redditmedia.com/vPh3wNPP5oqfsxJm5aHs2F7wbT8BWrNDoJNYx1DYdXA.png", "Offset": [-400, 0], "Size": [200, 200]}}},
  "/celestiapresents": {"Emotes": {"": {"Image": "//b.thumbs.redditmedia.com/TSkLNKAc_OHKjIgFh0vIX89QsvlkmHhBNeYw3Fu1i5o.png", "Offset": [-227, -725], "Size": [250, 179]}}},
  "/cellyshy": {"Emotes": {"": {"Image": "//b.thumbs.redditmedia.com/SpfstL_D0xmjEXXMht3KKJXCIxrTXf5vVVtQAG_gJjU.png", "Offset": [0, -200], "Size": [235, 250]}}},
  "/cheesesocks": {"Emotes": {"": {"Image": "//a.thumbs.redditmedia.com/if7jlDu9_S2gUGK3nvH0fMOA1WfSOX1FVGosl9MD_78.png", "Size": [200, 200]}}},
  "/cherry": {"Emotes": {"": {"Image": "//b.thumbs.redditmedia.com/R67XTkTAQExqJDkM.png", "Offset": [0, -450], "Size": [200, 250]}}},
  "/chinesenewyear": {"Emotes": {"": {"Image": "//b.thumbs.redditmedia.com/SpfstL_D0xmjEXXMht3KKJXCIxrTXf5vVVtQAG_gJjU.png", "Offset": [-235, -242], "Size": [160, 200]}}},
  "/chrysalispresents": {"Emotes": {"": {"Image": "//b.thumbs.redditmedia.com/DsWGGcXEX1Ug2P_GncrEAcvZCt5JykOOGdKkZwW9Tqk.png", "Offset": [0, -562], "Size": [158, 200]}}},
  "/chugchugchug": {"Emotes": {"": {"Image": "//f.thumbs.redditmedia.com/ACnoU0f8WOrMyXKq.png", "Size": [150, 116]}}},
  "/cleanfloor": {"Emotes": {"": {"Image": "//b.thumbs.redditmedia.com/usZx7PVZe254LpsWKoU4QR-y5QZuUMi5DDAcprjpe-Q.png", "Offset": [-200, -327], "Size": [200, 153]}}},
  "/cmonanon": {"Emotes": {"": {"Image": "//b.thumbs.redditmedia.com/usZx7PVZe254LpsWKoU4QR-y5QZuUMi5DDAcprjpe-Q.png", "Offset": [0, -619], "Size": [202, 250]}}},
  "/colgatepresents": {"Emotes": {"": {"Image": "//b.thumbs.redditmedia.com/jBJQjP68ypm1W6Nvpza13txBUgaQ8g21qlkSEvYkaKE.png", "Offset": [-198, -400], "Size": [200, 143]}}},
  "/colgatestroll": {"Emotes": {"": {"Image": "//b.thumbs.redditmedia.com/T6ZFnHbsQwhBNyGQUkw2_gzNSvKAI7_ofyoqHwEke2I.png", "Offset": [0, -528], "Size": [110, 200]}}},
  "/creammuffin": {"Emotes": {"": {"Image": "//a.thumbs.redditmedia.com/if7jlDu9_S2gUGK3nvH0fMOA1WfSOX1FVGosl9MD_78.png", "Offset": [-200, -400], "Size": [200, 200]}}},
  "/creamparty": {"Emotes": {"": {"Image": "//b.thumbs.redditmedia.com/kf2kLPkoDns8fsQMJK_lwyJ7x1YdccE8qnapjdjx_dA.png", "Offset": [-153, 0], "Size": [163, 200]}}},
  "/daringfinish": {"Emotes": {"": {"Image": "//b.thumbs.redditmedia.com/l1lKBLkm_jPDto3U5Wqv_6QNBPyssrk7uYudHYRZb2g.png", "Offset": [-187, -200], "Size": [193, 200]}}},
  "/derpbow": {"Emotes": {"": {"Image": "//b.thumbs.redditmedia.com/WqIlCIEaVlXodvMmdSSrNwzOogdcBlH99OKHHLG4aOQ.png", "Offset": [-312, -317], "Size": [172, 200]}}},
  "/derpyready": {"Emotes": {"": {"Image": "//b.thumbs.redditmedia.com/WqIlCIEaVlXodvMmdSSrNwzOogdcBlH99OKHHLG4aOQ.png", "Size": [143, 200]}}},
  "/dirtypinkie": {"Emotes": {"": {"Image": "//b.thumbs.redditmedia.com/vPh3wNPP5oqfsxJm5aHs2F7wbT8BWrNDoJNYx1DYdXA.png", "Size": [200, 200]}}},
  "/doalittleshake": {"Emotes": {"": {"Image": "//b.thumbs.redditmedia.com/W_wEuxMD4G8JNv9kl5K1WdN6iczgvYvCyaYVpF-NxHU.png", "Offset": [-184, -350], "Size": [200, 191]}}},
  "/donottaptheglass": {"Emotes": {"": {"Image": "//b.thumbs.redditmedia.com/jBJQjP68ypm1W6Nvpza13txBUgaQ8g21qlkSEvYkaKE.png", "Offset": [0, -450], "Size": [198, 200]}}},
  "/dontbeanass": {"Emotes": {"": {"Image": "//b.thumbs.redditmedia.com/DsWGGcXEX1Ug2P_GncrEAcvZCt5JykOOGdKkZwW9Tqk.png", "Offset": [0, -379], "Size": [250, 183]}}},
  "/doublemoon": {"Emotes": {"": {"Image": "//a.thumbs.redditmedia.com/if7jlDu9_S2gUGK3nvH0fMOA1WfSOX1FVGosl9MD_78.png", "Offset": [0, -200], "Size": [200, 200]}}},
  "/ediblelove": {"Emotes": {"": {"Image": "//b.thumbs.redditmedia.com/T6ZFnHbsQwhBNyGQUkw2_gzNSvKAI7_ofyoqHwEke2I.png", "Offset": [0, -180], "Size": [167, 200]}}},
  "/eevndrink": {"Emotes": {"": {"Image": "//b.thumbs.redditmedia.com/W_wEuxMD4G8JNv9kl5K1WdN6iczgvYvCyaYVpF-NxHU.png", "Size": [200, 166]}}},
  "/entertainme": {"Emotes": {"": {"Image": "//b.thumbs.redditmedia.com/Enb6P1KwmNZWrR1z-MlIF0yt_FL6Rgz_3iaTbzhmUts.png", "Size": [250, 213]}}},
  "/example6": {"Emotes": {"": {"Image": "//d.thumbs.redditmedia.com/3jN19HfmJYuskh1E.png", "Size": [300, 300]}}},
  "/examplecode1": {"Emotes": {"": {"Image": "//e.thumbs.redditmedia.com/0-LeTpXlBjdLjJgp.png", "Size": [70, 70]}}},
  "/examplecode2": {"Emotes": {"": {"Image": "//c.thumbs.redditmedia.com/T3T5hJ5ulBiCaoyb.png", "Size": [100, 100]}}},
  "/examplecode6": {"Emotes": {"": {"CSS": {"background-position": "0 0"}, "Type": "Custom"}}},
  "/facedownassup": {"Emotes": {"": {"Image": "//b.thumbs.redditmedia.com/T6ZFnHbsQwhBNyGQUkw2_gzNSvKAI7_ofyoqHwEke2I.png", "Size": [200, 180]}}},
  "/festivebuttplug": {"Emotes": {"": {"Image": "//a.thumbs.redditmedia.com/if7jlDu9_S2gUGK3nvH0fMOA1WfSOX1FVGosl9MD_78.png", "Offset": [-200, 0], "Size": [200, 200]}}},
  "/flutterplug": {"Emotes": {"": {"Image": "//b.thumbs.redditmedia.com/DsWGGcXEX1Ug2P_GncrEAcvZCt5JykOOGdKkZwW9Tqk.png", "Offset": [-250, -205], "Size": [200, 162]}}},
  "/fluttershypresents": {"Emotes": {"": {"Image": "//b.thumbs.redditmedia.com/usZx7PVZe254LpsWKoU4QR-y5QZuUMi5DDAcprjpe-Q.png", "Offset": [0, -421], "Size": [200, 198]}}},
  "/fucktheworld": {"Emotes": {"": {"Image": "//b.thumbs.redditmedia.com/T6ZFnHbsQwhBNyGQUkw2_gzNSvKAI7_ofyoqHwEke2I.png", "Offset": [-200, 0], "Size": [168, 200]}}},
  "/fullmoon": {"Emotes": {"": {"Image": "//b.thumbs.redditmedia.com/R67XTkTAQExqJDkM.png", "Offset": [-200, -450], "Size": [197, 250]}}},
  "/futaface": {"Emotes": {"": {"Image": "//b.thumbs.redditmedia.com/WqIlCIEaVlXodvMmdSSrNwzOogdcBlH99OKHHLG4aOQ.png", "Offset": [-162, -517], "Size": [200, 112]}}},
  "/futafap": {"Emotes": {"": {"Image": "//b.thumbs.redditmedia.com/Qqe0bVqoVMNKFAC_uuWC6v7ceF0BZbb9Asq5tMeKXIo.png", "Size": [250, 250]}}},
  "/futopen": {"Emotes": {"": {"Image": "//b.thumbs.redditmedia.com/Qqe0bVqoVMNKFAC_uuWC6v7ceF0BZbb9Asq5tMeKXIo.png", "Offset": [-250, 0], "Size": [250, 250]}}},
  "/ggnome": {"Emotes": {"": {"Image": "//b.thumbs.redditmedia.com/2hUZ7DpnWH9RktR_p9-79ZwJkeQCUEGF3O5Uo2XMiCk.png", "Offset": [0, -598], "Size": [170, 200]}}},
  "/hypercock": {"Emotes": {"": {"Image": "//b.thumbs.redditmedia.com/zaq8J0atNAFvcoaI9KE_2qIhhrPCMk6Wjt7NqFdWEjg.png", "Offset": [0, -631], "Size": [182, 200]}}},
  "/idreamofdashie": {"Emotes": {"": {"Image": "//b.thumbs.redditmedia.com/DsWGGcXEX1Ug2P_GncrEAcvZCt5JykOOGdKkZwW9Tqk.png", "Offset": [-307, 0], "Size": [124, 200]}}},
  "/injectiontime": {"Emotes": {"": {"Image": "//b.thumbs.redditmedia.com/zaq8J0atNAFvcoaI9KE_2qIhhrPCMk6Wjt7NqFdWEjg.png", "Offset": [-143, -431], "Size": [182, 200]}}},
  "/itschristmas": {"Emotes": {"": {"Image": "//b.thumbs.redditmedia.com/R67XTkTAQExqJDkM.png", "Offset": [0, -200], "Size": [187, 250]}}},
  "/kissmyass": {"Emotes": {"": {"Image": "//a.thumbs.redditmedia.com/if7jlDu9_S2gUGK3nvH0fMOA1WfSOX1FVGosl9MD_78.png", "Offset": [-400, -200], "Size": [200, 200]}}},
  "/kittiebelle": {"Emotes": {"": {"Image": "//b.thumbs.redditmedia.com/kf2kLPkoDns8fsQMJK_lwyJ7x1YdccE8qnapjdjx_dA.png", "Offset": [0, -450], "Size": [178, 200]}}},
  "/lickusclean": {"Emotes": {"": {"Image": "//b.thumbs.redditmedia.com/DQyr3kv0V18rANVNJimxQowdxtEjuLuflqEOactFMDo.png", "Offset": [-250, 0], "Size": [250, 250]}}},
  "/lovebutt": {"Emotes": {"": {"Image": "//b.thumbs.redditmedia.com/W_wEuxMD4G8JNv9kl5K1WdN6iczgvYvCyaYVpF-NxHU.png", "Offset": [-200, -150], "Size": [150, 200]}}},
  "/lunacock": {"Emotes": {"": {"Image": "//b.thumbs.redditmedia.com/vPh3wNPP5oqfsxJm5aHs2F7wbT8BWrNDoJNYx1DYdXA.png", "Offset": [-200, -200], "Size": [200, 200]}}},
  "/lunamine": {"Emotes": {"": {"Image": "//b.thumbs.redditmedia.com/Enb6P1KwmNZWrR1z-MlIF0yt_FL6Rgz_3iaTbzhmUts.png", "Offset": [0, -463], "Size": [194, 250]}}},
  "/lyracock": {"Emotes": {"": {"Image": "//b.thumbs.redditmedia.com/WqIlCIEaVlXodvMmdSSrNwzOogdcBlH99OKHHLG4aOQ.png", "Offset": [0, -600], "Size": [145, 250]}}},
  "/lyrapresents": {"Emotes": {"": {"Image": "//b.thumbs.redditmedia.com/zaq8J0atNAFvcoaI9KE_2qIhhrPCMk6Wjt7NqFdWEjg.png", "Size": [193, 139]}}},
  "/lyrish": {"Emotes": {"": {"Image": "//b.thumbs.redditmedia.com/usZx7PVZe254LpsWKoU4QR-y5QZuUMi5DDAcprjpe-Q.png", "Offset": [-200, -204], "Size": [200, 123]}}},
  "/magictrick": {"Emotes": {"": {"Image": "//b.thumbs.redditmedia.com/usZx7PVZe254LpsWKoU4QR-y5QZuUMi5DDAcprjpe-Q.png", "Offset": [0, -226], "Size": [200, 195]}}},
  "/maidmolly": {"Emotes": {"": {"Image": "//b.thumbs.redditmedia.com/TSkLNKAc_OHKjIgFh0vIX89QsvlkmHhBNeYw3Fu1i5o.png", "Offset": [-250, -475], "Size": [188, 250]}}},
  "/maudfinish": {"Emotes": {"": {"Image": "//b.thumbs.redditmedia.com/l1lKBLkm_jPDto3U5Wqv_6QNBPyssrk7uYudHYRZb2g.png", "Offset": [-256, 0], "Size": [157, 200]}}},
  "/minty": {"Emotes": {"": {"Image": "//b.thumbs.redditmedia.com/jBJQjP68ypm1W6Nvpza13txBUgaQ8g21qlkSEvYkaKE.png", "Offset": [-376, -200], "Size": [120, 200]}}},
  "/mistletoe": {"Emotes": {"": {"Image": "//b.thumbs.redditmedia.com/SpfstL_D0xmjEXXMht3KKJXCIxrTXf5vVVtQAG_gJjU.png", "Offset": [0, -450], "Size": [171, 200]}}},
  "/mooncock": {"Emotes": {"": {"CSS": {"background-position": "-155px -200px", "height": "234px", "width": "250px"}, "Type": "Custom"}}},
  "/mooncreampie": {"Emotes": {"": {"Image": "//b.thumbs.redditmedia.com/usZx7PVZe254LpsWKoU4QR-y5QZuUMi5DDAcprjpe-Q.png", "Offset": [0, -100], "Size": [200, 126]}}},
  "/more": {"Emotes": {"": {"Image": "//b.thumbs.redditmedia.com/TSkLNKAc_OHKjIgFh0vIX89QsvlkmHhBNeYw3Fu1i5o.png", "Offset": [0, -650], "Size": [227, 250]}}},
  "/nightcest": {"Emotes": {"": {"Image": "//b.thumbs.redditmedia.com/vPh3wNPP5oqfsxJm5aHs2F7wbT8BWrNDoJNYx1DYdXA.png", "Offset": [-200, 0], "Size": [200, 200]}}},
  "/nmanal": {"Emotes": {"": {"Image": "//b.thumbs.redditmedia.com/usZx7PVZe254LpsWKoU4QR-y5QZuUMi5DDAcprjpe-Q.png", "Offset": [-200, 0], "Size": [250, 204]}}},
  "/nmcock": {"Emotes": {"": {"Image": "//b.thumbs.redditmedia.com/WqIlCIEaVlXodvMmdSSrNwzOogdcBlH99OKHHLG4aOQ.png", "Offset": [-275, 0], "Size": [124, 150]}}},
  "/nmmbent": {"Emotes": {"": {"Image": "//b.thumbs.redditmedia.com/TSkLNKAc_OHKjIgFh0vIX89QsvlkmHhBNeYw3Fu1i5o.png", "Offset": [-225, 0], "Size": [182, 225]}}},
  "/nmmbj": {"Emotes": {"": {"Image": "//b.thumbs.redditmedia.com/TSkLNKAc_OHKjIgFh0vIX89QsvlkmHhBNeYw3Fu1i5o.png", "Size": [225, 193]}}},
  "/nmmpresenting": {"Emotes": {"": {"CSS": {"background-position": "-100% -200%"}, "Type": "Custom"}}},
  "/nmmpresents": {"Emotes": {"": {"Image": "//b.thumbs.redditmedia.com/DQyr3kv0V18rANVNJimxQowdxtEjuLuflqEOactFMDo.png", "Offset": [-500, -250], "Size": [250, 250]}}},
  "/piledriver": {"Emotes": {"": {"Image": "//b.thumbs.redditmedia.com/SpfstL_D0xmjEXXMht3KKJXCIxrTXf5vVVtQAG_gJjU.png", "Offset": [0, -650], "Size": [214, 250]}}},
  "/pillowtalk": {"Emotes": {"": {"Image": "//b.thumbs.redditmedia.com/jBJQjP68ypm1W6Nvpza13txBUgaQ8g21qlkSEvYkaKE.png", "Offset": [-161, -200], "Size": [215, 200]}}},
  "/pinkiepanties": {"Emotes": {"": {"Image": "//b.thumbs.redditmedia.com/Qqe0bVqoVMNKFAC_uuWC6v7ceF0BZbb9Asq5tMeKXIo.png", "Offset": [-500, 0], "Size": [250, 250]}}},
  "/pinkiepop": {"Emotes": {"": {"Image": "//b.thumbs.redditmedia.com/DQyr3kv0V18rANVNJimxQowdxtEjuLuflqEOactFMDo.png", "Offset": [-750, -250], "Size": [250, 250]}}},
  "/pinkiepresents": {"Emotes": {"": {"Image": "//b.thumbs.redditmedia.com/R67XTkTAQExqJDkM.png", "Offset": [0, -700], "Size": [170, 200]}}},
  "/plotpair": {"Emotes": {"": {"Image": "//b.thumbs.redditmedia.com/DQyr3kv0V18rANVNJimxQowdxtEjuLuflqEOactFMDo.png", "Size": [250, 250]}}},
  "/pm": {"Emotes": {"": {"Image": "//a.thumbs.redditmedia.com/if7jlDu9_S2gUGK3nvH0fMOA1WfSOX1FVGosl9MD_78.png", "Offset": [0, -600], "Size": [200, 200]}}},
  "/ppready": {"Emotes": {"": {"Image": "//b.thumbs.redditmedia.com/7cYpsGICiW7W-bCp30OqnE9WgFgXLCA6XWiImG2BuLE.png", "Offset": [-150, -150], "Size": [150, 150]}}},
  "/presentingcolgate": {"Emotes": {"": {"Image": "//b.thumbs.redditmedia.com/T6ZFnHbsQwhBNyGQUkw2_gzNSvKAI7_ofyoqHwEke2I.png", "Offset": [-250, -351], "Size": [200, 157]}}},
  "/princesshug": {"Emotes": {"": {"Image": "//b.thumbs.redditmedia.com/7cYpsGICiW7W-bCp30OqnE9WgFgXLCA6XWiImG2BuLE.png", "Offset": [-300, 0], "Size": [150, 150]}}},
  "/pussylantern": {"Emotes": {"": {"Image": "//b.thumbs.redditmedia.com/jBJQjP68ypm1W6Nvpza13txBUgaQ8g21qlkSEvYkaKE.png", "Offset": [-158, 0], "Size": [148, 150]}}},
  "/queenass": {"Emotes": {"": {"Image": "//b.thumbs.redditmedia.com/jBJQjP68ypm1W6Nvpza13txBUgaQ8g21qlkSEvYkaKE.png", "Offset": [0, -250], "Size": [161, 200]}}},
  "/queendrip": {"Emotes": {"": {"Image": "//b.thumbs.redditmedia.com/Enb6P1KwmNZWrR1z-MlIF0yt_FL6Rgz_3iaTbzhmUts.png", "Offset": [-194, -494], "Size": [167, 200]}}},
  "/queennurse": {"Emotes": {"": {"Image": "//b.thumbs.redditmedia.com/R67XTkTAQExqJDkM.png", "Offset": [-187, -200], "Size": [195, 250]}}},
  "/queenopenwide": {"Emotes": {"": {"Image": "//b.thumbs.redditmedia.com/vPh3wNPP5oqfsxJm5aHs2F7wbT8BWrNDoJNYx1DYdXA.png", "Offset": [0, -200], "Size": [200, 200]}}},
  "/queenpresents": {"Emotes": {"": {"Image": "//b.thumbs.redditmedia.com/R67XTkTAQExqJDkM.png", "Offset": [-251, 0], "Size": [250, 200]}}},
  "/rainbowmaid": {"Emotes": {"": {"Image": "//b.thumbs.redditmedia.com/SpfstL_D0xmjEXXMht3KKJXCIxrTXf5vVVtQAG_gJjU.png", "Offset": [-171, -450], "Size": [190, 200]}}},
  "/raricock": {"Emotes": {"": {"Image": "//b.thumbs.redditmedia.com/jBJQjP68ypm1W6Nvpza13txBUgaQ8g21qlkSEvYkaKE.png", "Size": [158, 250]}}},
  "/rarieyes": {"Emotes": {"": {"Image": "//b.thumbs.redditmedia.com/l1lKBLkm_jPDto3U5Wqv_6QNBPyssrk7uYudHYRZb2g.png", "Offset": [-250, -400], "Size": [126, 150]}}},
  "/rarifinish": {"Emotes": {"": {"Image": "//b.thumbs.redditmedia.com/Enb6P1KwmNZWrR1z-MlIF0yt_FL6Rgz_3iaTbzhmUts.png", "Offset": [0, -213], "Size": [236, 250]}}},
  "/rarisuck": {"Emotes": {"": {"Image": "//b.thumbs.redditmedia.com/Enb6P1KwmNZWrR1z-MlIF0yt_FL6Rgz_3iaTbzhmUts.png", "Offset": [0, -713], "Size": [150, 125]}}},
  "/rdxxxmas": {"Emotes": {"": {"Image": "//b.thumbs.redditmedia.com/WqIlCIEaVlXodvMmdSSrNwzOogdcBlH99OKHHLG4aOQ.png", "Offset": [-162, -317], "Size": [150, 200]}}},
  "/rocksoff": {"Emotes": {"": {"Image": "//b.thumbs.redditmedia.com/WqIlCIEaVlXodvMmdSSrNwzOogdcBlH99OKHHLG4aOQ.png", "Offset": [-143, 0], "Size": [132, 150]}}},
  "/royalflush": {"Emotes": {"": {"Image": "//b.thumbs.redditmedia.com/TSkLNKAc_OHKjIgFh0vIX89QsvlkmHhBNeYw3Fu1i5o.png", "Offset": [0, -475], "Size": [250, 175]}}},
  "/rubydrip": {"Emotes": {"": {"Image": "//b.thumbs.redditmedia.com/_sJ6RIQzUs76jyIdOP5QKbrmPZQL5GJ9KMNmVKjm-4c.png", "Offset": [-200, 0], "Size": [184, 200]}}},
  "/rule63": {"Emotes": {"": {"Image": "//b.thumbs.redditmedia.com/T6ZFnHbsQwhBNyGQUkw2_gzNSvKAI7_ofyoqHwEke2I.png", "Offset": [-168, -200], "Size": [250, 151]}}},
  "/scootabutt": {"Emotes": {"": {"Image": "//b.thumbs.redditmedia.com/_sJ6RIQzUs76jyIdOP5QKbrmPZQL5GJ9KMNmVKjm-4c.png", "Size": [200, 191]}}},
  "/seductivecadance": {"Emotes": {"": {"Image": "//b.thumbs.redditmedia.com/7cYpsGICiW7W-bCp30OqnE9WgFgXLCA6XWiImG2BuLE.png", "Offset": [-150, 0], "Size": [150, 150]}}},
  "/sexhappened": {"Emotes": {"": {"Image": "//b.thumbs.redditmedia.com/_sJ6RIQzUs76jyIdOP5QKbrmPZQL5GJ9KMNmVKjm-4c.png", "Offset": [-227, -200], "Size": [200, 177]}}},
  "/sexygaming": {"Emotes": {"": {"Image": "//a.thumbs.redditmedia.com/if7jlDu9_S2gUGK3nvH0fMOA1WfSOX1FVGosl9MD_78.png", "Offset": [-400, -400], "Size": [200, 200]}}},
  "/sexyzecoramaid": {"Emotes": {"": {"Image": "//b.thumbs.redditmedia.com/2hUZ7DpnWH9RktR_p9-79ZwJkeQCUEGF3O5Uo2XMiCk.png", "Offset": [-348, -150], "Size": [135, 150]}}},
  "/sffinish": {"Emotes": {"": {"Image": "//b.thumbs.redditmedia.com/l1lKBLkm_jPDto3U5Wqv_6QNBPyssrk7uYudHYRZb2g.png", "Offset": [0, -150], "Size": [187, 250]}}},
  "/shakethatass": {"Emotes": {"": {"Image": "//a.thumbs.redditmedia.com/lkJaetAxPZP17SV3Ud50-XlMSAnMvFGCJpyLKhUdM-0.png", "Size": [250, 250]}}},
  "/shybelle": {"Emotes": {"": {"Image": "//b.thumbs.redditmedia.com/kf2kLPkoDns8fsQMJK_lwyJ7x1YdccE8qnapjdjx_dA.png", "Offset": [-200, -650], "Size": [146, 150]}}},
  "/shybloom": {"Emotes": {"": {"Image": "//b.thumbs.redditmedia.com/kf2kLPkoDns8fsQMJK_lwyJ7x1YdccE8qnapjdjx_dA.png", "Offset": [-178, -434], "Size": [167, 200]}}},
  "/shykisscock": {"Emotes": {"": {"Image": "//b.thumbs.redditmedia.com/7cYpsGICiW7W-bCp30OqnE9WgFgXLCA6XWiImG2BuLE.png", "Size": [150, 150]}}},
  "/sisterlylove": {"Emotes": {"": {"Image": "//b.thumbs.redditmedia.com/SpfstL_D0xmjEXXMht3KKJXCIxrTXf5vVVtQAG_gJjU.png", "Offset": [-164, 0], "Size": [200, 150]}}},
  "/smugass": {"Emotes": {"": {"Image": "//b.thumbs.redditmedia.com/SpfstL_D0xmjEXXMht3KKJXCIxrTXf5vVVtQAG_gJjU.png", "Size": [164, 200]}}},
  "/sonatass": {"Emotes": {"": {"Image": "//b.thumbs.redditmedia.com/jBJQjP68ypm1W6Nvpza13txBUgaQ8g21qlkSEvYkaKE.png", "Offset": [-306, 0], "Size": [147, 200]}}},
  "/spitbutt": {"Emotes": {"": {"Image": "//b.thumbs.redditmedia.com/W_wEuxMD4G8JNv9kl5K1WdN6iczgvYvCyaYVpF-NxHU.png", "Offset": [0, -166], "Size": [200, 171]}}},
  "/spitdom": {"Emotes": {"": {"Image": "//b.thumbs.redditmedia.com/W_wEuxMD4G8JNv9kl5K1WdN6iczgvYvCyaYVpF-NxHU.png", "Offset": [0, -337], "Size": [184, 200]}}},
  "/spreadingcadance": {"Emotes": {"": {"Image": "//b.thumbs.redditmedia.com/7cYpsGICiW7W-bCp30OqnE9WgFgXLCA6XWiImG2BuLE.png", "Offset": [0, -150], "Size": [150, 150]}}},
  "/ssfinish": {"Emotes": {"": {"Image": "//b.thumbs.redditmedia.com/WqIlCIEaVlXodvMmdSSrNwzOogdcBlH99OKHHLG4aOQ.png", "Offset": [0, -400], "Size": [162, 199]}}},
  "/starburstseduce": {"Emotes": {"": {"Image": "//b.thumbs.redditmedia.com/Enb6P1KwmNZWrR1z-MlIF0yt_FL6Rgz_3iaTbzhmUts.png", "Offset": [-236, -294], "Size": [132, 200]}}},
  "/stripeass": {"Emotes": {"": {"Image": "//b.thumbs.redditmedia.com/2hUZ7DpnWH9RktR_p9-79ZwJkeQCUEGF3O5Uo2XMiCk.png", "Size": [250, 198]}}},
  "/suckitcowboy": {"Emotes": {"": {"Image": "//b.thumbs.redditmedia.com/zaq8J0atNAFvcoaI9KE_2qIhhrPCMk6Wjt7NqFdWEjg.png", "Offset": [0, -139], "Size": [195, 200]}}},
  "/sunandmoon": {"Emotes": {"": {"Image": "//b.thumbs.redditmedia.com/TSkLNKAc_OHKjIgFh0vIX89QsvlkmHhBNeYw3Fu1i5o.png", "Offset": [-144, -225], "Size": [200, 250]}}},
  "/suncock": {"Emotes": {"": {"Image": "//b.thumbs.redditmedia.com/l1lKBLkm_jPDto3U5Wqv_6QNBPyssrk7uYudHYRZb2g.png", "Size": [106, 150]}}},
  "/sweetiebutt": {"Emotes": {"": {"Image": "//b.thumbs.redditmedia.com/kf2kLPkoDns8fsQMJK_lwyJ7x1YdccE8qnapjdjx_dA.png", "Offset": [0, -650], "Size": [200, 188]}}},
  "/switchyorgy": {"Emotes": {"": {"Image": "//b.thumbs.redditmedia.com/_sJ6RIQzUs76jyIdOP5QKbrmPZQL5GJ9KMNmVKjm-4c.png", "Offset": [0, -616], "Size": [195, 200]}}},
  "/tailwraps": {"Emotes": {"": {"Image": "//b.thumbs.redditmedia.com/usZx7PVZe254LpsWKoU4QR-y5QZuUMi5DDAcprjpe-Q.png", "Size": [200, 100]}}},
  "/tavipanties": {"Emotes": {"": {"Image": "//b.thumbs.redditmedia.com/W_wEuxMD4G8JNv9kl5K1WdN6iczgvYvCyaYVpF-NxHU.png", "Offset": [-200, 0], "Size": [139, 150]}}},
  "/tdschoolfillies": {"Emotes": {"": {"Image": "//b.thumbs.redditmedia.com/NdRjG0oKiEC8mFD6jvOegC7CwTS_QMVyfBjv5sq6wIs.png", "Offset": [-137, -600], "Size": [261, 200]}}},
  "/tiapresenting": {"Emotes": {"": {"Image": "//a.thumbs.redditmedia.com/if7jlDu9_S2gUGK3nvH0fMOA1WfSOX1FVGosl9MD_78.png", "Offset": [0, -400], "Size": [200, 200]}}},
  "/tootight": {"Emotes": {"": {"Image": "//b.thumbs.redditmedia.com/DQyr3kv0V18rANVNJimxQowdxtEjuLuflqEOactFMDo.png", "Offset": [-500, 0], "Size": [250, 250]}}},
  "/trixiecum": {"Emotes": {"": {"Image": "//b.thumbs.redditmedia.com/DsWGGcXEX1Ug2P_GncrEAcvZCt5JykOOGdKkZwW9Tqk.png", "Offset": [-250, -367], "Size": [200, 166]}}},
  "/trixiefinish": {"Emotes": {"": {"Image": "//b.thumbs.redditmedia.com/Enb6P1KwmNZWrR1z-MlIF0yt_FL6Rgz_3iaTbzhmUts.png", "Offset": [-250, 0], "Size": [250, 177]}}},
  "/trixiefun": {"Emotes": {"": {"Image": "//b.thumbs.redditmedia.com/zaq8J0atNAFvcoaI9KE_2qIhhrPCMk6Wjt7NqFdWEjg.png", "Offset": [0, -339], "Size": [143, 200]}}},
  "/trixiepresents": {"Emotes": {"": {"Image": "//b.thumbs.redditmedia.com/R67XTkTAQExqJDkM.png", "Size": [250, 200]}}},
  "/trixiespread": {"Emotes": {"": {"Image": "//b.thumbs.redditmedia.com/_sJ6RIQzUs76jyIdOP5QKbrmPZQL5GJ9KMNmVKjm-4c.png", "Offset": [0, -200], "Size": [227, 250]}}},
  "/twibadteacher": {"Emotes": {"": {"Image": "//b.thumbs.redditmedia.com/NdRjG0oKiEC8mFD6jvOegC7CwTS_QMVyfBjv5sq6wIs.png", "Offset": [-176, 0], "Size": [186, 200]}}},
  "/twibegentle": {"Emotes": {"": {"Image": "//b.thumbs.redditmedia.com/NdRjG0oKiEC8mFD6jvOegC7CwTS_QMVyfBjv5sq6wIs.png", "Offset": [0, -350], "Size": [118, 150]}}},
  "/twichug": {"Emotes": {"": {"Image": "//f.thumbs.redditmedia.com/ACnoU0f8WOrMyXKq.png", "Size": [150, 116]}}},
  "/twidrip": {"Emotes": {"": {"Image": "//b.thumbs.redditmedia.com/NdRjG0oKiEC8mFD6jvOegC7CwTS_QMVyfBjv5sq6wIs.png", "Size": [176, 200]}}},
  "/twifinish": {"Emotes": {"": {"Image": "//b.thumbs.redditmedia.com/l1lKBLkm_jPDto3U5Wqv_6QNBPyssrk7uYudHYRZb2g.png", "Offset": [-106, 0], "Size": [150, 112]}}},
  "/twihearts": {"Emotes": {"": {"Image": "//b.thumbs.redditmedia.com/DsWGGcXEX1Ug2P_GncrEAcvZCt5JykOOGdKkZwW9Tqk.png", "Offset": [-169, 0], "Size": [135, 200]}}},
  "/twilicornpeek": {"Emotes": {"": {"Image": "//b.thumbs.redditmedia.com/NdRjG0oKiEC8mFD6jvOegC7CwTS_QMVyfBjv5sq6wIs.png", "Offset": [-188, -200], "Size": [209, 200]}}},
  "/twilightsuckit": {"Emotes": {"": {"Image": "//b.thumbs.redditmedia.com/_sJ6RIQzUs76jyIdOP5QKbrmPZQL5GJ9KMNmVKjm-4c.png", "Offset": [-227, -377], "Size": [189, 200]}}},
  "/twipanties": {"Emotes": {"": {"Image": "//b.thumbs.redditmedia.com/NdRjG0oKiEC8mFD6jvOegC7CwTS_QMVyfBjv5sq6wIs.png", "Offset": [0, -200], "Size": [188, 150]}}},
  "/twipresents": {"Emotes": {"": {"Image": "//b.thumbs.redditmedia.com/WqIlCIEaVlXodvMmdSSrNwzOogdcBlH99OKHHLG4aOQ.png", "Offset": [-143, -150], "Size": [200, 167]}}},
  "/twisockpresents": {"Emotes": {"": {"Image": "//b.thumbs.redditmedia.com/NdRjG0oKiEC8mFD6jvOegC7CwTS_QMVyfBjv5sq6wIs.png", "Offset": [0, -500], "Size": [137, 300]}}},
  "/twisockspresenting": {"Emotes": {"": {"Image": "//b.thumbs.redditmedia.com/SpfstL_D0xmjEXXMht3KKJXCIxrTXf5vVVtQAG_gJjU.png", "Offset": [-235, -150], "Size": [200, 98]}}},
  "/twispread": {"Emotes": {"": {"Image": "//b.thumbs.redditmedia.com/NdRjG0oKiEC8mFD6jvOegC7CwTS_QMVyfBjv5sq6wIs.png", "Offset": [-137, -400], "Size": [226, 200]}}},
  "/vanal": {"Emotes": {"": {"Image": "//b.thumbs.redditmedia.com/kf2kLPkoDns8fsQMJK_lwyJ7x1YdccE8qnapjdjx_dA.png", "Size": [153, 200]}}},
  "/vsdrip": {"Emotes": {"": {"Image": "//b.thumbs.redditmedia.com/kf2kLPkoDns8fsQMJK_lwyJ7x1YdccE8qnapjdjx_dA.png", "Offset": [0, -200], "Size": [155, 250]}}},
  "/vsshower": {"Emotes": {"": {"Image": "//b.thumbs.redditmedia.com/WqIlCIEaVlXodvMmdSSrNwzOogdcBlH99OKHHLG4aOQ.png", "Offset": [0, -201], "Size": [141, 200]}}},
  "/wetcora": {"Emotes": {"": {"Image": "//b.thumbs.redditmedia.com/DQyr3kv0V18rANVNJimxQowdxtEjuLuflqEOactFMDo.png", "Offset": [0, -250], "Size": [250, 250]}}},
  "/wetmoons": {"Emotes": {"": {"Image": "//a.thumbs.redditmedia.com/if7jlDu9_S2gUGK3nvH0fMOA1WfSOX1FVGosl9MD_78.png", "Offset": [-200, -200], "Size": [200, 200]}}},
  "/wetqueen": {"Emotes": {"": {"Image": "//a.thumbs.redditmedia.com/if7jlDu9_S2gUGK3nvH0fMOA1WfSOX1FVGosl9MD_78.png", "Offset": [-400, 0], "Size": [200, 200]}}},
  "/whosaysyouhaveachoice": {"Emotes": {"": {"Image": "//b.thumbs.redditmedia.com/W_wEuxMD4G8JNv9kl5K1WdN6iczgvYvCyaYVpF-NxHU.png", "Offset": [-350, 0], "Size": [133, 200]}}},
  "/wonderjob": {"Emotes": {"": {"Image": "//b.thumbs.redditmedia.com/l1lKBLkm_jPDto3U5Wqv_6QNBPyssrk7uYudHYRZb2g.png", "Offset": [0, -625], "Size": [200, 167]}}},
  "/zecoraanal": {"Emotes": {"": {"Image": "//b.thumbs.redditmedia.com/2hUZ7DpnWH9RktR_p9-79ZwJkeQCUEGF3O5Uo2XMiCk.png", "Offset": [0, -398], "Size": [198, 200]}}},
  "/zecoraoops": {"Emotes": {"": {"Image": "//b.thumbs.redditmedia.com/2hUZ7DpnWH9RktR_p9-79ZwJkeQCUEGF3O5Uo2XMiCk.png", "Offset": [0, -198], "Size": [198, 200]}}}
}