{
  "/Thumb": {"Emotes": {"": {"CSS": {"background-image": "url(\"http://a.thumbs.redditmedia.com/4TspFoQhr5qPtCZr.png\")", "background-repeat": "no-repeat", "clear": "none", "display": "block", "float": "left"}, "Type": "Custom"}}},
  "/gcadorkable": {"Emotes": {"": {"Image": "http://a.thumbs.redditmedia.com/4TspFoQhr5qPtCZr.png", "Offset": [-5, -5], "Size": [70, 91]}}},
  "/gcangry": {"Emotes": {"": {"Image": "http://a.thumbs.redditmedia.com/4TspFoQhr5qPtCZr.png", "Offset": [-85, -5], "Size": [70, 66]}}},
  "/gcconfident": {"Emotes": {"": {"Image": "http://a.thumbs.redditmedia.com/4TspFoQhr5qPtCZr.png", "Offset": [-165, -5], "Size": [70, 68]}}},
  "/gcfacehoof": {"Emotes": {"": {"Image": "http://a.thumbs.redditmedia.com/4TspFoQhr5qPtCZr.png", "Offset": [-245, -5], "Size": [70, 70]}}},
  "/gchmm": {"Emotes": {"": {"Image": "http://a.thumbs.redditmedia.com/4TspFoQhr5qPtCZr.png", "Offset": [-325, -5], "Size": [70, 70]}}},
  "/gcrevelation": {"Emotes": {"": {"Image": "http://a.thumbs.redditmedia.com/4TspFoQhr5qPtCZr.png", "Offset": [-405, -5], "Size": [70, 104]}}},
  "/gcrock": {"Emotes": {"": {"Image": "http://a.thumbs.redditmedia.com/4TspFoQhr5qPtCZr.png", "Offset": [-485, -5], "Size": [70, 112]}}},
  "/gcsmug": {"Emotes": {"": {"Image": "http://a.thumbs.redditmedia.com/4TspFoQhr5qPtCZr.png", "Offset": [-565, -5], "Size": [70, 78]}}},
  "/gcwoo": {"Emotes": {"": {"Image": "http://a.thumbs.redditmedia.com/4TspFoQhr5qPtCZr.png", "Offset": [-645, -5], "Size": [70, 73]}}},
  "/gcyummy": {"Emotes": {"": {"Image": "http://a.thumbs.redditmedia.com/4TspFoQhr5qPtCZr.png", "Offset": [-85, -88], "Size": [70, 129]}}},
  "/mintcopy": {"Emotes": {"": {"Image": "http://a.thumbs.redditmedia.com/4TspFoQhr5qPtCZr.png", "Offset": [-165, -88], "Size": [70, 70]}}},
  "/minthappy": {"Emotes": {"": {"Image": "http://a.thumbs.redditmedia.com/4TspFoQhr5qPtCZr.png", "Offset": [-245, -88], "Size": [70, 70]}}},
  "/mintmad": {"Emotes": {"": {"Image": "http://a.thumbs.redditmedia.com/4TspFoQhr5qPtCZr.png", "Offset": [-325, -88], "Size": [70, 70]}}},
  "/mintsad": {"Emotes": {"": {"Image": "http://a.thumbs.redditmedia.com/4TspFoQhr5qPtCZr.png", "Offset": [-645, -88], "Size": [70, 70]}}},
  "/mintthink": {"Emotes": {"": {"Image": "http://a.thumbs.redditmedia.com/4TspFoQhr5qPtCZr.png", "Offset": [-5, -168], "Size": [70, 70]}}},
  "/nhpoker": {"Emotes": {"": {"Image": "http://b.thumbs.redditmedia.com/20Rz9okzE67QaAiQ.png", "Offset": [-5, -5], "Size": [150, 170]}}},
  "/nighttimesalute": {"Emotes": {"": {"Image": "http://a.thumbs.redditmedia.com/4TspFoQhr5qPtCZr.png", "Offset": [-165, -168], "Size": [70, 57]}}},
  "/nimblefun": {"Emotes": {"": {"Image": "http://a.thumbs.redditmedia.com/4TspFoQhr5qPtCZr.png", "Offset": [-245, -168], "Size": [150, 101]}}},
  "/paigehappy": {"Emotes": {"": {"Image": "http://a.thumbs.redditmedia.com/4TspFoQhr5qPtCZr.png", "Offset": [-405, -168], "Size": [70, 83]}}},
  "/paigeyell": {"Emotes": {"": {"Image": "http://a.thumbs.redditmedia.com/4TspFoQhr5qPtCZr.png", "Offset": [-485, -168], "Size": [70, 82]}}},
  "/rubybendover": {"Emotes": {"": {"Image": "http://a.thumbs.redditmedia.com/4TspFoQhr5qPtCZr.png", "Offset": [-565, -168], "Size": [150, 112]}}},
  "/rubyprimp": {"Emotes": {"": {"Image": "http://a.thumbs.redditmedia.com/4TspFoQhr5qPtCZr.png", "Offset": [-5, -290], "Size": [70, 70]}}},
  "/rubyreally": {"Emotes": {"": {"Image": "http://a.thumbs.redditmedia.com/4TspFoQhr5qPtCZr.png", "Offset": [-85, -290], "Size": [70, 78]}}},
  "/rubysmirk": {"Emotes": {"": {"Image": "http://a.thumbs.redditmedia.com/4TspFoQhr5qPtCZr.png", "Offset": [-165, -290], "Size": [70, 80]}}},
  "/sebored": {"Emotes": {"": {"Image": "http://a.thumbs.redditmedia.com/4TspFoQhr5qPtCZr.png", "Offset": [-245, -290], "Size": [70, 56]}}},
  "/sehahaha": {"Emotes": {"": {"Image": "http://a.thumbs.redditmedia.com/4TspFoQhr5qPtCZr.png", "Offset": [-325, -290], "Size": [70, 70]}}},
  "/sesly": {"Emotes": {"": {"Image": "http://a.thumbs.redditmedia.com/4TspFoQhr5qPtCZr.png", "Offset": [-405, -290], "Size": [70, 70]}}},
  "/sscaketopper": {"Emotes": {"": {"Image": "http://a.thumbs.redditmedia.com/4TspFoQhr5qPtCZr.png", "Offset": [-485, -290], "Size": [70, 70]}}},
  "/starstrucksuave": {"Emotes": {"": {"Image": "http://a.thumbs.redditmedia.com/4TspFoQhr5qPtCZr.png", "Offset": [-565, -290], "Size": [70, 70]}}},
  "/sugarbutt": {"Emotes": {"": {"Image": "http://a.thumbs.redditmedia.com/4TspFoQhr5qPtCZr.png", "Offset": [-245, -370], "Size": [150, 88]}}},
  "/sugarfree": {"Emotes": {"": {"Image": "http://a.thumbs.redditmedia.com/4TspFoQhr5qPtCZr.png", "Offset": [-645, -290], "Size": [70, 70]}}},
  "/sugarico": {"Emotes": {"": {"Image": "http://a.thumbs.redditmedia.com/4TspFoQhr5qPtCZr.png", "Offset": [-5, -370], "Size": [70, 70]}}},
  "/sugarscared": {"Emotes": {"": {"Image": "http://a.thumbs.redditmedia.com/4TspFoQhr5qPtCZr.png", "Offset": [-405, -370], "Size": [70, 70]}}},
  "/sugarsmarm": {"Emotes": {"": {"Image": "http://a.thumbs.redditmedia.com/4TspFoQhr5qPtCZr.png", "Offset": [-485, -370], "Size": [70, 70]}}},
  "/sugarsmile": {"Emotes": {"": {"Image": "http://a.thumbs.redditmedia.com/4TspFoQhr5qPtCZr.png", "Offset": [-565, -370], "Size": [70, 70]}}},
  "/sugarwut": {"Emotes": {"": {"Image": "http://a.thumbs.redditmedia.com/4TspFoQhr5qPtCZr.png", "Offset": [-645, -370], "Size": [70, 82]}}},
  "/swordbashful": {"Emotes": {"": {"Image": "http://a.thumbs.redditmedia.com/4TspFoQhr5qPtCZr.png", "Offset": [-5, -462], "Size": [70, 70]}}},
  "/swordbee": {"Emotes": {"": {"Image": "http://a.thumbs.redditmedia.com/4TspFoQhr5qPtCZr.png", "Offset": [-85, -462], "Size": [101, 77]}}},
  "/swordfacehoof": {"Emotes": {"": {"Image": "http://a.thumbs.redditmedia.com/4TspFoQhr5qPtCZr.png", "Offset": [-405, -462], "Size": [70, 70]}}},
  "/swordgrr": {"Emotes": {"": {"Image": "http://a.thumbs.redditmedia.com/4TspFoQhr5qPtCZr.png", "Offset": [-485, -462], "Size": [70, 70]}}},
  "/swordguilt": {"Emotes": {"": {"Image": "http://a.thumbs.redditmedia.com/4TspFoQhr5qPtCZr.png", "Offset": [-565, -462], "Size": [70, 70]}}},
  "/swordlie": {"Emotes": {"": {"Image": "http://a.thumbs.redditmedia.com/4TspFoQhr5qPtCZr.png", "Offset": [-645, -462], "Size": [70, 65]}}},
  "/swordmad": {"Emotes": {"": {"Image": "http://a.thumbs.redditmedia.com/4TspFoQhr5qPtCZr.png", "Offset": [-196, -537], "Size": [70, 70]}}},
  "/swordmirror": {"Emotes": {"": {"Image": "http://a.thumbs.redditmedia.com/4TspFoQhr5qPtCZr.png", "Offset": [-276, -537], "Size": [112, 150]}}},
  "/swordpride": {"Emotes": {"": {"Image": "http://a.thumbs.redditmedia.com/4TspFoQhr5qPtCZr.png", "Offset": [-645, -537], "Size": [100, 158]}}},
  "/swordsad": {"Emotes": {"": {"Image": "http://a.thumbs.redditmedia.com/4TspFoQhr5qPtCZr.png", "Offset": [-725, -5], "Size": [70, 70]}}},
  "/swordscowl": {"Emotes": {"": {"Image": "http://a.thumbs.redditmedia.com/4TspFoQhr5qPtCZr.png", "Offset": [-725, -85], "Size": [70, 70]}}},
  "/swordseesham": {"Emotes": {"": {"Image": "http://a.thumbs.redditmedia.com/4TspFoQhr5qPtCZr.png", "Offset": [-805, -5], "Size": [150, 149]}}},
  "/swordshock": {"Emotes": {"": {"Image": "http://a.thumbs.redditmedia.com/4TspFoQhr5qPtCZr.png", "Offset": [-805, -164], "Size": [70, 70]}}},
  "/swordshrug": {"Emotes": {"": {"Image": "http://a.thumbs.redditmedia.com/4TspFoQhr5qPtCZr.png", "Offset": [-885, -164], "Size": [70, 70]}}},
  "/swordspear": {"Emotes": {"": {"Image": "http://a.thumbs.redditmedia.com/4TspFoQhr5qPtCZr.png", "Offset": [-725, -244], "Size": [170, 189]}}},
  "/swordstare": {"Emotes": {"": {"Image": "http://a.thumbs.redditmedia.com/4TspFoQhr5qPtCZr.png", "Offset": [-755, -443], "Size": [150, 149]}}},
  "/swordsuave": {"Emotes": {"": {"Image": "http://a.thumbs.redditmedia.com/4TspFoQhr5qPtCZr.png", "Offset": [-5, -602], "Size": [150, 174]}}},
  "/sworduham": {"Emotes": {"": {"Image": "http://a.thumbs.redditmedia.com/4TspFoQhr5qPtCZr.png", "Offset": [-905, -244], "Size": [70, 70]}}},
  "/swordulan": {"Emotes": {"": {"Image": "http://a.thumbs.redditmedia.com/4TspFoQhr5qPtCZr.png", "Offset": [-398, -602], "Size": [100, 133]}}},
  "/synpoker": {"Emotes": {"": {"Image": "http://a.thumbs.redditmedia.com/4TspFoQhr5qPtCZr.png", "Offset": [-905, -324], "Size": [70, 70]}}},
  "/synponder": {"Emotes": {"": {"Image": "http://a.thumbs.redditmedia.com/4TspFoQhr5qPtCZr.png", "Offset": [-915, -404], "Size": [70, 70]}}},
  "/synsquint": {"Emotes": {"": {"Image": "http://a.thumbs.redditmedia.com/4TspFoQhr5qPtCZr.png", "Offset": [-915, -484], "Size": [70, 70]}}},
  "/syntaxadorkable": {"Emotes": {"": {"Image": "http://a.thumbs.redditmedia.com/4TspFoQhr5qPtCZr.png", "Offset": [-508, -564], "Size": [70, 116]}}},
  "/syntaxderp": {"Emotes": {"": {"Image": "http://a.thumbs.redditmedia.com/4TspFoQhr5qPtCZr.png", "Offset": [-915, -564], "Size": [70, 70]}}},
  "/thiskillsthegame": {"Emotes": {"": {"Image": "http://a.thumbs.redditmedia.com/4TspFoQhr5qPtCZr.png", "Offset": [-165, -644], "Size": [70, 75]}}},
  "/thunderdrink": {"Emotes": {"": {"Image": "http://a.thumbs.redditmedia.com/4TspFoQhr5qPtCZr.png", "Offset": [-755, -644], "Size": [70, 99]}}},
  "/thunderwut": {"Emotes": {"": {"CSS": {"background-position": "-835px -644px", "height": "92px", "width": "70px"}, "Type": "Custom"}}}
}