{
"/banexie": ["+trixie"],
"/berrypunchcolgatenuzzle": ["+berrypunch", "+colgate"],
"/bpandchug": ["+berrypunch", "+colgate"],
"/braeburn1": ["+braeburn"],
"/braeburnaloo": ["+braeburn", "+scootaloo"],
"/braeburneyes": ["+braeburn", "+rarity"],
"/braescrunch": ["+braeburn"],
"/braesoarhug": ["+braeburn", "+soarin"],
"/braesoarnuzzle": ["+braeburn", "+soarin"],
"/braetavia": ["+braeburn", "+octavia"],
"/braewhat": ["+braeburn"],
"/brushingtime": ["+colgate"],
"/colgatechristmas": ["+colgate"],
"/colgatederp": ["+colgate"],
"/colgatepunchsnuggle": ["+berrypunch", "+colgate"],
"/colgateworry": ["+colgate"],
"/colgatongue": ["+colgate"],
"/colno": ["+colgate"],
"/crystalcolgate": ["+colgate"],
"/crystals": ["+filly", "+kingsombra"],
"/dabrushie": ["+colgate"],
"/drinkxie": ["+trixie"],
"/evilmilkshake": ["+filly", "+kingsombra"],
"/fetaltrixie": ["+trixie"],
"/flutterburn": ["+braeburn", "+fluttershy"],
"/gayburn": ["+braeburn"],
"/hellosexy": ["+braeburn", "+pinkamina", "+pinkiepie"],
"/hithere": ["+braeburn"],
"/littlestrongburn": ["+braeburn", "+otherpony"],
"/partygate": ["+colgate"],
"/pearlywhites": ["+colgate"],
"/rifleburn": ["+braeburn"],
"/righthere": ["+colgate"],
"/scootaburn": ["+braeburn"],
"/scrunchycolgate": ["+colgate"],
"/sexyburn": ["+braeburn"],
"/sittrixie": ["+trixie"],
"/snailburn": ["+braeburn", "+mashup"],
"/snakeburn": ["+braeburn", "+mashup"],
"/sockybrushie": ["+colgate"],
"/sombragrin": ["+kingsombra"],
"/switchedroles": ["+braeburn", "+soarin"],
"/teenagebraeburn": ["+braeburn"],
"/trixinsane": ["+trixie"],
"/whynotcolgate": ["+colgate"],
"/yallbrushing": ["+colgate"],
"/yummybrush": ["+colgate"]
}