{
"/discannoyed": ["+discord"],
"/discawesome": ["+discord"],
"/discbeam": ["+discord"],
"/disccute": ["+discord"],
"/discevil": ["+discord"],
"/discfear": ["+discord"],
"/discfrustrated": ["+discord"],
"/discfurious": ["+discord"],
"/discgeneral": ["+discord"],
"/discglasses": ["+discord"],
"/discimply": ["+discord"],
"/discjustsayin": ["+discord"],
"/disckisses": ["+discord"],
"/disclestia": ["+discord"],
"/discofficer": ["+discord"],
"/discponder": ["+discord"],
"/discponymad": ["+discord"],
"/discponyreally": ["+discord"],
"/discponysad": ["+discord"],
"/discponyscowl": ["+discord"],
"/discponyscrunch": ["+discord"],
"/discponysmile": ["+discord"],
"/discponyunsure": ["+discord"],
"/discponywhat": ["+discord"],
"/discrage": ["+discord"],
"/discreally": ["+discord"],
"/discshock": ["+discord"],
"/discsinister": ["+discord"],
"/discsmile": ["+discord"],
"/discsmirk": ["+discord"],
"/discsmug": ["+discord"],
"/discsquint": ["+discord"],
"/discstare": ["+discord"],
"/discswag": ["+discord"],
"/disctea": ["+discord"],
"/discthatsnice": ["+discord"],
"/discwhat": ["+discord"],
"/discwhyyouarewrong": ["+discord"],
"/discwtf": ["+discord"],
"/discyousee": ["+discord"]
}