{
"/battlestance": ["+ocpony"],
"/female2": ["+nonpony"],
"/female3": ["+nonpony"],
"/female4": ["+nonpony"],
"/female5": ["+nonpony"],
"/female6": ["+nonpony"],
"/female7": ["+nonpony"],
"/female8": ["+nonpony"],
"/hamntor": ["+ocpony"],
"/himntor": ["+ocpony"],
"/iseeham": ["+ocpony"],
"/male1": ["+nonpony"],
"/male10": ["+nonpony"],
"/male11": ["+nonpony"],
"/male12": ["+nonpony"],
"/male13": ["+nonpony"],
"/male14": ["+nonpony"],
"/male15": ["+nonpony"],
"/male16": ["+nonpony"],
"/male17": ["+nonpony"],
"/male18": ["+nonpony"],
"/male19": ["+nonpony"],
"/male2": ["+nonpony"],
"/male20": ["+nonpony"],
"/male3": ["+nonpony"],
"/male5": ["+nonpony"],
"/male6": ["+nonpony"],
"/male7": ["+nonpony"],
"/male8": ["+nonpony"],
"/male9": ["+nonpony"],
"/perry": ["+nonpony"],
"/sadmonogram": ["+nonpony"],
"/swordattack": ["+ocpony"],
"/swordbee": ["+ocpony"],
"/swordberg": ["+ocpony"],
"/swordcrazy": ["+ocpony"],
"/swordguilt": ["+ocpony"],
"/swordhoof": ["+ocpony"],
"/swordlie": ["+ocpony"],
"/swordmad": ["+ocpony"],
"/swordsad": ["+ocpony"],
"/swordserious": ["+ocpony"],
"/swordshock": ["+ocpony"],
"/swordshrug": ["+ocpony", "+shrug"],
"/swordsmile": ["+ocpony"],
"/swordsmug": ["+ocpony"],
"/swordsquint": ["+ocpony"],
"/swordtux": ["+ocpony"],
"/swordulan": ["+ocpony"],
"/swordy": ["+ocpony"]
}